LICENSE
MANIFEST.in
README.rst
setup.cfg
setup.py
cross_correlation/Analyze_CCF.py
cross_correlation/CCF_Systematics.py
cross_correlation/CCF_Widget.py
cross_correlation/Correct_CCF_Temperatures.py
cross_correlation/Correlate.py
cross_correlation/GenericSearch.py
cross_correlation/Normalized_Xcorr.py
cross_correlation/__init__.py
fitters/__init__.py
fitters/bayesian.py
fitters/linear.py
gullikson_scripts.egg-info/PKG-INFO
gullikson_scripts.egg-info/SOURCES.txt
gullikson_scripts.egg-info/dependency_links.txt
gullikson_scripts.egg-info/requires.txt
gullikson_scripts.egg-info/top_level.txt
isochrone_helpers/Feiden.py
isochrone_helpers/__init__.py
spectral_type/Mamajek_Table.py
spectral_type/SpectralTypeRelations.py
spectral_type/__init__.py
spectral_type/data/Mamajek_Table.txt
spectral_type/data/Pecaut2013.tsv
stellar_data/__init__.py
stellar_data/creators.py
stellar_data/readers.py
stellar_data/data/Stars.sqlite
stellar_models/Broaden.py
stellar_models/RotBroad.py
stellar_models/RotBroad2.pyx
stellar_models/StellarModel.py
stellar_models/__init__.py
utils/DataStructures.py
utils/FittingUtilities.pyx
utils/HDF5_Helpers.py
utils/HelperFunctions.py
utils/IMF_utils.py
utils/PlotBlackbodies.py
utils/StarData.py
utils/Units.py
utils/__init__.py
utils/plottools.py
utils/readmultispec.py